mcp_weather_http/__init__.py
mcp_weather_http/__main__.py
mcp_weather_http/server.py
mcp_weather_http0_tr0e-1.0.0.1.dist-info/METADATA
mcp_weather_http0_tr0e-1.0.0.1.dist-info/WHEEL
mcp_weather_http0_tr0e-1.0.0.1.dist-info/entry_points.txt
mcp_weather_http0_tr0e-1.0.0.1.dist-info/top_level.txt
mcp_weather_http0_tr0e-1.0.0.1.dist-info/RECORD
